rencrypt-1.2.2.dist-info/METADATA
rencrypt-1.2.2.dist-info/WHEEL
rencrypt-1.2.2.dist-info/license_files/LICENSE-Apache-2.0
rencrypt-1.2.2.dist-info/license_files/LICENSE-MIT
rencrypt/__init__.py
rencrypt/rencrypt.cpython-39-darwin.so
rencrypt-1.2.2.dist-info/RECORD
